MonteCarloCSV/CsvService.py
MonteCarloCSV/MonteCarloService.py
MonteCarloCSV/WorkItem.py
MonteCarloCSV/__init__.py
MonteCarloCSV/logo.png
MonteCarloCSV/main.py
montecarlocsv-1.0.5.dist-info/LICENSE
montecarlocsv-1.0.5.dist-info/METADATA
montecarlocsv-1.0.5.dist-info/WHEEL
montecarlocsv-1.0.5.dist-info/entry_points.txt
montecarlocsv-1.0.5.dist-info/top_level.txt
montecarlocsv-1.0.5.dist-info/RECORD
