Metadata-Version: 2.1
Name: montecarlocsv
Version: 1.0.5
Summary: A package to generate Monte Carlo Simulations from CSV files.
Home-page: https://letpeople.work
Author: Benjamin Huser-Berta
Author-email: benj.huser@gmail.com
Classifier: Programming Language :: Python :: 3
Classifier: License :: OSI Approved :: MIT License
Classifier: Operating System :: OS Independent
Requires-Python: >=3.9
License-File: LICENSE
Requires-Dist: argparse
Requires-Dist: pandas
Requires-Dist: numpy
Requires-Dist: matplotlib
